lupin_danquin/__init__.py
lupin_danquin/__main__.py
lupin_danquin/run.py
lupin_danquin/core/__init__.py
lupin_danquin/core/application.py
lupin_danquin/core/global_variable.py
lupin_danquin/core/line_ended.py
lupin_danquin/core/local_variable.py
lupin_danquin/core/parameter.py
lupin_danquin/core/program.py
lupin_danquin/core/rules.py
lupin_danquin/core/coding_rules_validator/__init__.py
lupin_danquin/core/coding_rules_validator/coging_rules_validator.py
lupin_danquin/core/tools/__init__.py
lupin_danquin/core/tools/utils.py
lupin_danquin/core/val3_doc_generator/__init__.py
lupin_danquin/core/val3_doc_generator/val3_doc_generator.py
lupin_danquin/templates/val3_documentation_md.j2
lupin_danquin-1.0.6.dist-info/LICENCE
lupin_danquin-1.0.6.dist-info/METADATA
lupin_danquin-1.0.6.dist-info/WHEEL
lupin_danquin-1.0.6.dist-info/entry_points.txt
lupin_danquin-1.0.6.dist-info/top_level.txt
lupin_danquin-1.0.6.dist-info/RECORD
